{
  "clinics": [
    {
      "name": "Blu Odontologia",
      "Google_Ads_id": "9842118482",
      "Meta_Ads_id": "1027042954330340"
    },
    {
      "name": "Aquarius",
      "Google_Ads_id": "9699495311",
      "Meta_Ads_id": "785914302775317"
    },
    {
      "name": "Billig Odontologia",
      "Google_Ads_id": null,
      "Meta_Ads_id": "869196310911024"
    },
    {
      "name": "Ideal Odontologia",
      "Google_Ads_id": null,
      "Meta_Ads_id": "2641279129517249"
    },
    {
      "name": "AME Odontologia",
      "Google_Ads_id": "3154371978",
      "Meta_Ads_id": "2545064879227291"
    },
    {
      "name": "MAG Odontologia",
      "Google_Ads_id": "9792933205",
      "Meta_Ads_id": "907724290439237"
    },
    {
      "name": "Oral Artt",
      "Google_Ads_id": null,
      "Meta_Ads_id": "1420921588657020"
    },
    {
      "name": "Prime+",
      "Google_Ads_id": null,
      "Meta_Ads_id": "1366792541582087"
    },
    {
      "name": "Royal Implantes",
      "Google_Ads_id": "2800770276",
      "Meta_Ads_id": "1160020696295686"
    },
    {
      "name": "Instituto Evoluer",
      "Google_Ads_id": null,
      "Meta_Ads_id": "813841904691777"
    },
    {
      "name": "Implantar",
      "Google_Ads_id": null,
      "Meta_Ads_id": "1489460565345585"
    },
    {
      "name": "A1 Implantes",
      "Google_Ads_id": "5063918962",
      "Meta_Ads_id": "201060786265666"
    },
    {
      "name": "OdontoRibas",
      "Google_Ads_id": null,
      "Meta_Ads_id": "570467326096876"
    },
    {
      "name": "Chroma",
      "Google_Ads_id": null,
      "Meta_Ads_id": "2392590024426959"
    },
    {
      "name": "Ágora Odontologia",
      "Google_Ads_id": "8243438509",
      "Meta_Ads_id": null
    },
    {
      "name": "Àquila Odontologia",
      "Google_Ads_id": null,
      "Meta_Ads_id": "405903702355858"
    },
    {
      "name": "Odonto Mauá",
      "Google_Ads_id": null,
      "Meta_Ads_id": "1182470030645595"
    },
    {
      "name": "Elysium Odontologia",
      "Google_Ads_id": null,
      "Meta_Ads_id": "950569036717304"
    },
    {
      "name": "Ortho Certo",
      "Google_Ads_id": null,
      "Meta_Ads_id": "1116837743850314"
    },
    {
      "name": "Odonto Gline",
      "Google_Ads_id": null,
      "Meta_Ads_id": "965619185145281"
    },
    {
      "name": "RVS Odontologia",
      "Google_Ads_id": null,
      "Meta_Ads_id": "1004620391382061"
    },
    {
      "name": "Lumine Odontologia",
      "Google_Ads_id": "6824239391",
      "Meta_Ads_id": "1489460565345585"
    },
    {
      "name": "Dra. Helainy",
      "Google_Ads_id": null,
      "Meta_Ads_id": "721512803415550"
    },
    {
      "name": "Voito Odontologia",
      "Google_Ads_id": "1373102348",
      "Meta_Ads_id": "1827307410922831"
    },
    {
      "name": "Prime MT",
      "Google_Ads_id": "7954202137",
      "Meta_Ads_id": "1281333339536378"
    },
    {
      "name": "Dens Odontologia",
      "Google_Ads_id": "9637396609",
      "Meta_Ads_id": "1247958619490898"
    }
  ]
}